django_redissearch/__init__.py
django_redissearch-0.0.1.dist-info/METADATA
django_redissearch-0.0.1.dist-info/WHEEL
django_redissearch-0.0.1.dist-info/top_level.txt
django_redissearch-0.0.1.dist-info/RECORD
